ivy/__init__.py
ivy/backend.py
ivy/context.py
ivy/context_provider.py
ivy/loop.py
ivy/workflow_manager.py
ivy/cli/__init__.py
ivy/cli/main.py
ivy/config/__init__.py
ivy/config/base_config.py
ivy/config/workflow_config_parallel.py
ivy/exceptions/__init__.py
ivy/exceptions/exceptions.py
ivy/plugin/__init__.py
ivy/plugin/base_plugin.py
ivy/plugin/parallel_plugin_collection.py
ivy/plugin/plugin_factory.py
ivy/plugin/range_map_plugin.py
ivy/plugin/show_stats.py
ivy/plugin/show_summary_stats.py
ivy/plugin/simple_square_plugin.py
ivy/plugin/sum_reduce_plugin.py
ivy/utils/__init__.py
ivy/utils/stop_criteria.py
ivy/utils/struct.py
ivy/utils/timing.py
ivy/utils/utils.py
tests/__init__.py
tests/test_ContextProvider.py
tests/test_Loop.py
tests/test_ParallelPluginCollection.py
tests/test_Pickle.py
tests/test_PluginFactory.py
tests/test_SimplePlugin.py
tests/test_StopCriteria.py
tests/test_WorkflowStruct.py
tests/test_cli.py
tests/test_context.py
tests/test_execute.py
tests/test_show_summary_stats_plugin.py
tests/test_utils.py
tests/test_workflow_manager.py
tests/config/__init__.py
tests/config/workflow_config.py
tests/config/workflow_config_args.py
tests/config/workflow_config_cli.py
tests/config/workflow_config_cust.py
tests/config/workflow_config_execute.py
tests/config/workflow_config_execute_loop.py
tests/config/workflow_config_parallel.py
tests/config/workflow_config_simple.py
tests/plugin/__init__.py
tests/plugin/execute_plugin.py
tests/plugin/range_map_plugin.py
tests/plugin/simple_plugin.py
tests/plugin/simple_square_plugin.py
tests/plugin/sum_reduce_plugin.py
ivy_wfengine-0.4.0.dist-info/AUTHORS.rst
ivy_wfengine-0.4.0.dist-info/LICENSE
ivy_wfengine-0.4.0.dist-info/METADATA
ivy_wfengine-0.4.0.dist-info/WHEEL
ivy_wfengine-0.4.0.dist-info/entry_points.txt
ivy_wfengine-0.4.0.dist-info/top_level.txt
ivy_wfengine-0.4.0.dist-info/RECORD
