Metadata-Version: 2.1
Name: ivy-wfengine
Version: 0.4.0
Summary: Simple and flexible workflow engine
Home-page: https://cosmo-gitlab.phys.ethz.ch/cosmo/ivy
Author: Joel Akeret
Author-email: jakeret@phys.ethz.ch
License: Proprietary
Keywords: ivy
Classifier: Development Status :: 2 - Pre-Alpha
Classifier: Intended Audience :: Science/Research
Classifier: Intended Audience :: Developers
Classifier: License :: OSI Approved :: MIT License
Classifier: Natural Language :: English
Classifier: Programming Language :: Python :: 3.6
License-File: LICENSE
License-File: AUTHORS.rst
